cloudvps/__init__.py
cloudvps/api.py
cloudvps/cloudctl.py
cloudvps/objects/__init__.py
cloudvps/objects/actions.py
cloudvps/objects/base.py
cloudvps/objects/common.py
cloudvps/objects/history.py
cloudvps/objects/images.py
cloudvps/objects/snapshots.py
cloudvps/objects/ssh_keys.py
cloudvps/objects/vps.py
api_cloudvps_py-0.1.7.dist-info/LICENSE
api_cloudvps_py-0.1.7.dist-info/METADATA
api_cloudvps_py-0.1.7.dist-info/WHEEL
api_cloudvps_py-0.1.7.dist-info/top_level.txt
api_cloudvps_py-0.1.7.dist-info/RECORD
