Metadata-Version: 2.1
Name: api-cloudvps-py
Version: 0.1.7
Summary: Basic api client for reg.ru cloudvps
Home-page: https://github.com/wa-pis/api-cloudvps-py
Author: Anton Grudin
Author-email: onepis2word@gmail.com
License: MIT
Keywords: api-client api python requests reg.ru kvm cloud
Platform: UNKNOWN
Classifier: Development Status :: 4 - Beta
Classifier: Intended Audience :: Developers
Classifier: Topic :: Software Development
Classifier: Topic :: Internet :: WWW/HTTP
Classifier: Natural Language :: Russian
Classifier: License :: OSI Approved :: MIT License
Classifier: Programming Language :: Python :: 2
Classifier: Programming Language :: Python :: 2.7
Classifier: Programming Language :: Python :: 3
Classifier: Programming Language :: Python :: 3.4
Classifier: Programming Language :: Python :: 3.5
Classifier: Programming Language :: Python :: 3.6
Classifier: Programming Language :: Python :: 3.7
Requires-Dist: requests
Requires-Dist: future
